README.rst
setup.py
src/zdas/__init__.py
src/zdas/base.py
src/zdas/tests.py
src/zdas.egg-info/PKG-INFO
src/zdas.egg-info/SOURCES.txt
src/zdas.egg-info/dependency_links.txt
src/zdas.egg-info/not-zip-safe
src/zdas.egg-info/requires.txt
src/zdas.egg-info/top_level.txt