Metadata-Version: 1.1
Name: zdas
Version: 0.1.1
Summary: Zencore daemon application start.
Home-page: https://github.com/appstore-zencore/zdas.git
Author: zencore
Author-email: dobetter@zencore.cn
License: MIT
Keywords: zdas
Platform: UNKNOWN
Classifier: Development Status :: 5 - Production/Stable
Classifier: Intended Audience :: Developers
Classifier: Topic :: Software Development :: Libraries :: Python Modules
Classifier: License :: OSI Approved :: MIT License
Classifier: Programming Language :: Python :: 3
Classifier: Programming Language :: Python :: 3 :: Only
Requires: six
Requires: psutil
